<?xml version="1.0" encoding="utf-8" standalone="yes"?>
<Gesture Name = "Redo">
	<Stroke>
		<Point X = "878,0612" Y = "1538,077" T = "0" Pressure = "0" />
		<Point X = "964,9847" Y = "1520,685" T = "0" Pressure = "0" />
		<Point X = "1049,149" Y = "1511,556" T = "0" Pressure = "0" />
		<Point X = "1147,601" Y = "1499,663" T = "0" Pressure = "0" />
		<Point X = "1257,614" Y = "1479,929" T = "0" Pressure = "0" />
		<Point X = "1374,641" Y = "1451,085" T = "0" Pressure = "0" />
		<Point X = "1441,536" Y = "1418,981" T = "0" Pressure = "0" />
		<Point X = "1396,804" Y = "1363,693" T = "0" Pressure = "0" />
		<Point X = "1315,864" Y = "1344,496" T = "0" Pressure = "0" />
		<Point X = "1234,714" Y = "1328,825" T = "0" Pressure = "0" />
		<Point X = "1146,247" Y = "1307,41" T = "0" Pressure = "0" />
		<Point X = "1060,562" Y = "1281,943" T = "0" Pressure = "0" />
		<Point X = "931,9383" Y = "1238,281" T = "0" Pressure = "0" />
	</Stroke>
</Gesture>
