<?xml version="1.0" encoding="utf-8" standalone="yes"?>
<Gesture Name = "VRDrawLines">
	<Stroke>
		<Point X = "975,1302" Y = "1335,315" T = "0" Pressure = "0" />
		<Point X = "985,2747" Y = "1363,851" T = "0" Pressure = "0" />
		<Point X = "997,3184" Y = "1393,603" T = "0" Pressure = "0" />
		<Point X = "1019,438" Y = "1445,343" T = "0" Pressure = "0" />
		<Point X = "1043,937" Y = "1495,3" T = "0" Pressure = "0" />
		<Point X = "1067,005" Y = "1524,281" T = "0" Pressure = "0" />
		<Point X = "1100,004" Y = "1567,889" T = "0" Pressure = "0" />
		<Point X = "1139,336" Y = "1592,594" T = "0" Pressure = "0" />
		<Point X = "1172,522" Y = "1603,064" T = "0" Pressure = "0" />
		<Point X = "1201,168" Y = "1614,367" T = "0" Pressure = "0" />
		<Point X = "1233,688" Y = "1610,33" T = "0" Pressure = "0" />
		<Point X = "1270,359" Y = "1602,7" T = "0" Pressure = "0" />
		<Point X = "1310,538" Y = "1585,695" T = "0" Pressure = "0" />
		<Point X = "1335,779" Y = "1561,537" T = "0" Pressure = "0" />
		<Point X = "1369,477" Y = "1531,343" T = "0" Pressure = "0" />
		<Point X = "1393,23" Y = "1500,417" T = "0" Pressure = "0" />
		<Point X = "1407,251" Y = "1463,396" T = "0" Pressure = "0" />
		<Point X = "1412,662" Y = "1424,868" T = "0" Pressure = "0" />
		<Point X = "1414,867" Y = "1381,592" T = "0" Pressure = "0" />
		<Point X = "1412,32" Y = "1330,401" T = "0" Pressure = "0" />
		<Point X = "1404,317" Y = "1291,164" T = "0" Pressure = "0" />
		<Point X = "1398,166" Y = "1256,464" T = "0" Pressure = "0" />
		<Point X = "1396,79" Y = "1225,903" T = "0" Pressure = "0" />
		<Point X = "1392,776" Y = "1203,451" T = "0" Pressure = "0" />
		<Point X = "1385,819" Y = "1183,349" T = "0" Pressure = "0" />
		<Point X = "1390,829" Y = "1169,782" T = "0" Pressure = "0" />
		<Point X = "1389,242" Y = "1184,13" T = "0" Pressure = "0" />
	</Stroke>
</Gesture>
